SL_Asset_Sentiment/OWEngSent.py
SL_Asset_Sentiment/OWSent.py
SL_Asset_Sentiment/__init__.py
SL_Asset_Sentiment-1.4.0.dist-info/LICENSE.txt
SL_Asset_Sentiment-1.4.0.dist-info/METADATA
SL_Asset_Sentiment-1.4.0.dist-info/WHEEL
SL_Asset_Sentiment-1.4.0.dist-info/top_level.txt
SL_Asset_Sentiment-1.4.0.dist-info/RECORD
