Metadata-Version: 2.1
Name: SL-Asset-Sentiment
Version: 1.4.0
Summary: SL Asset Sentiment Analysis
Home-page: UNKNOWN
Author: Steven Wang
Author-email: 
License: UNKNOWN
Platform: UNKNOWN
Classifier: Programming Language :: Python :: 3
Classifier: License :: OSI Approved :: MIT License
Classifier: Operating System :: OS Independent
